[
	{ "s": "PARITY", "p": [25] },
	{ "s": "PASSWORD", "p": [25] },
	{ "s": "PER", "p": [57, 52] },
	{ "s": "PID", "p": [22] },
	{ "s": "PORT", "p": [17] },
	{ "s": "POSTGRE", "p": [4] },
	{ "s": "PRO", "p": [5] },
	{ "s": "PROCESSES", "p": [2] },
	{ "s": "PRODUCTION", "p": [23, 17] },
	{ "s": "PROFESSIONAL", "p": [5] },
	{ "s": "PROGRAM", "p": [57, 52, 17] },
	{ "s": "PROGRAMDATA", "p": [17, 53, 60, 59] },
	{ "s": "PROGRAMDATA\\X-TENSIVE\\DPA\\CONFIG\\DPASERVER.CONFIG", "p": [17] },
	{ "s": "PROGRAMDATA\\X-TENSIVE\\DPA\\INSTALLERS", "p": [60] },
	{ "s": "PROGRAMDATA\\X-TENSIVE\\DPA\\LOGGING", "p": [59, 53] },
	{ "s": "PROGRAMDATA\\XTENSIVE\\PROJECT109\\LOGS", "p": [53] },
	{ "s": "PROJECT109", "p": [53] },
	{ "s": "PUBLIC", "p": [60, 54] }
]