[
	{ "s": "ШАБЛОН", "p": [36, 42, 106, 94, 83, 43] },
	{ "s": "ШАБЛОНА", "p": [46, 45, 44, 43, 42, 106, 36] },
	{ "s": "ШАБЛОНОВ", "p": [31, 17, 42] },
	{ "s": "ШАБЛОНЫ", "p": [36, 42, 43, 34, 31, 17, 83, 35] },
	{ "s": "ШАГ", "p": [23, 30, 25, 40, 20, 104, 87, 63, 43, 33, 21, 64, 13] },
	{ "s": "ШАГАМИ", "p": [15] },
	{ "s": "ШАГЕ", "p": [13, 71, 51, 16] },
	{ "s": "ШАГИ", "p": [17] },
	{ "s": "ШАГОВ", "p": [13] },
	{ "s": "ШАГОМ", "p": [75, 33, 19] },
	{ "s": "ШАГУ", "p": [108] },
	{ "s": "ШЕЛ", "p": [110] },
	{ "s": "ШЕСТЕРЕНКУ", "p": [80, 78] },
	{ "s": "ШЕСТНАДЦАТЕРИЧНЫЕ", "p": [32] },
	{ "s": "ШИНА", "p": [70] },
	{ "s": "ШИНЫ", "p": [82] },
	{ "s": "ШИФРОВАНИЯ", "p": [27] },
	{ "s": "ШКАЛЕ", "p": [36] },
	{ "s": "ШКАЛОЙ", "p": [35] },
	{ "s": "ШКАЛУ", "p": [34] },
	{ "s": "ШКАЛЫ", "p": [108, 35] },
	{ "s": "ШЛЮЗ", "p": [73, 72] },
	{ "s": "ШПИНДЕЛЕЙ", "p": [80] },
	{ "s": "ШПИНДЕЛЬ", "p": [106, 96, 93] },
	{ "s": "ШПИНДЕЛЮ", "p": [96] },
	{ "s": "ШПИНДЕЛЯ", "p": [96, 106, 93] },
	{ "s": "ШТАТНОГО", "p": [60, 54, 2] },
	{ "s": "ШТАТНОЙ", "p": [61, 58, 53, 50] },
	{ "s": "ШТРИХ", "p": [31] },
	{ "s": "ШТРИХ-КОДУ", "p": [31] },
	{ "s": "ШТУК", "p": [110] },
	{ "s": "ШТУКА", "p": [106] },
	{ "s": "ШТУКИ", "p": [88] }
]