[
	{ "s": "К", "p": [31, 107, 12, 81, 58, 53, 7, 23, 92, 78, 63, 51, 36, 33, 32, 28, 109, 102, 91, 85, 77, 74, 71, 69, 27, 19, 16, 10, 105, 104, 103, 101, 99, 97, 96, 90, 89, 86, 84, 83, 82, 75, 73, 72, 70, 66, 65, 64, 60, 54, 43, 39, 38, 34, 24, 21, 14, 13, 11, 5, 2] },
	{ "s": "КАБИНЕТЕ", "p": [21] },
	{ "s": "КАВЫЧКАМИ", "p": [81] },
	{ "s": "КАВЫЧКАХ", "p": [81] },
	{ "s": "КАЖДАЯ", "p": [85] },
	{ "s": "КАЖДОГО", "p": [107, 83, 81, 22] },
	{ "s": "КАЖДОЕ", "p": [95] },
	{ "s": "КАЖДОЙ", "p": [107] },
	{ "s": "КАЖДОМ", "p": [100] },
	{ "s": "КАЖДОМУ", "p": [102, 100, 97, 93, 85, 81] },
	{ "s": "КАЖДЫЙ", "p": [107, 106] },
	{ "s": "КАК", "p": [107, 27, 78, 40, 102, 95, 81, 71, 69, 68, 63, 61, 59, 48, 32, 31, 25, 20, 16, 12, 4] },
	{ "s": "КАКИЕ", "p": [62, 107, 102, 86, 55, 43] },
	{ "s": "КАКИМИ", "p": [32] },
	{ "s": "КАКИХ", "p": [101, 99, 95, 62, 107] },
	{ "s": "КАКИХ-ЛИБО", "p": [62] },
	{ "s": "КАКОГО", "p": [13, 14] },
	{ "s": "КАКОЙ", "p": [102, 100, 95] },
	{ "s": "КАКОМУ", "p": [94] },
	{ "s": "КАКОМУ-ЛИБО", "p": [94] },
	{ "s": "КАКУЮ", "p": [112] },
	{ "s": "КАМЕРЫ", "p": [38] },
	{ "s": "КАНАЛ", "p": [68, 112] },
	{ "s": "КАНАЛ2", "p": [68] },
	{ "s": "КАНАЛА", "p": [68] },
	{ "s": "КАНАЛЕ", "p": [68] },
	{ "s": "КАНАЛОВ", "p": [68, 80] },
	{ "s": "КАНАЛЫ", "p": [68] },
	{ "s": "КАРАНДАШ", "p": [36] },
	{ "s": "КАРТ", "p": [98, 4] },
	{ "s": "КАРТОЧЕК", "p": [89] },
	{ "s": "КАРТОЧКА", "p": [93, 100] },
	{ "s": "КАРТОЧКАМИ", "p": [87] },
	{ "s": "КАРТОЧКЕ", "p": [93, 100, 89] },
	{ "s": "КАРТОЧКИ", "p": [107, 31] },
	{ "s": "КАРТОЧКУ", "p": [100, 93] },
	{ "s": "КАРТУ", "p": [7, 102] },
	{ "s": "КАТАЛОГ", "p": [106, 85, 78] },
	{ "s": "КАТАЛОГА", "p": [27, 85] },
	{ "s": "КАТАЛОГАМИ", "p": [85] },
	{ "s": "КАТАЛОГЕ", "p": [85] },
	{ "s": "КАТАЛОГИ", "p": [85] },
	{ "s": "КАТЕГОРИИ", "p": [107, 103, 89, 93] },
	{ "s": "КАТЕГОРИЙ", "p": [107, 85, 31] },
	{ "s": "КАТЕГОРИЮ", "p": [90] },
	{ "s": "КАТЕГОРИЯ", "p": [84, 85] },
	{ "s": "КАТЕГОРИЯМ", "p": [107, 103, 23] },
	{ "s": "КАЧЕСТВА", "p": [107, 103, 111, 2] },
	{ "s": "КАЧЕСТВЕ", "p": [70, 90, 80, 78, 51, 49, 43, 35, 28] },
	{ "s": "КАЧЕСТВО", "p": [89] },
	{ "s": "КЛАВИШ", "p": [81] },
	{ "s": "КЛАССИФИКАЦИИ", "p": [27, 110, 89, 92] },
	{ "s": "КЛАССИФИКАЦИЮ", "p": [27] },
	{ "s": "КЛАССИФИКАЦИЯ", "p": [110, 90, 87, 27, 89, 64] },
	{ "s": "КЛАССИФИЦИРОВАННЫЕ", "p": [110] },
	{ "s": "КЛАССИФИЦИРОВАТЬ", "p": [27, 92, 84] },
	{ "s": "КЛАССИЧЕСКИМИ", "p": [2] },
	{ "s": "КЛИЕНТА", "p": [4] },
	{ "s": "КЛИЕНТСКИЕ", "p": [85] },
	{ "s": "КЛИК", "p": [97, 105, 95, 92, 66, 65, 64, 43, 39, 38, 104, 49, 31, 24] },
	{ "s": "КЛИКА", "p": [65] },
	{ "s": "КЛИКНИТЕ", "p": [92, 26] },
	{ "s": "КЛИКНУЛИ", "p": [81] },
	{ "s": "КЛИКНУТЬ", "p": [57, 52, 40] },
	{ "s": "КЛОНИРОВАНИЕ", "p": [105] },
	{ "s": "КЛОНИРОВАННОЙ", "p": [105] },
	{ "s": "КЛОНИРОВАТЬ", "p": [105] },
	{ "s": "КЛЮЧ", "p": [21] },
	{ "s": "КЛЮЧА", "p": [21] },
	{ "s": "КНОПКА", "p": [102, 36, 105, 76] },
	{ "s": "КНОПКАМИ", "p": [107, 92, 104, 71] },
	{ "s": "КНОПКИ", "p": [104, 107, 89, 88, 43, 13, 105, 95, 76, 74, 71, 46, 44] },
	{ "s": "КНОПКОЙ", "p": [107, 95, 65, 97, 92, 105, 89, 66, 64, 43, 39, 38, 104, 96, 80, 63, 57, 52, 49, 48, 40, 31, 30, 26, 24] },
	{ "s": "КНОПКУ", "p": [97, 95, 43, 92, 105, 88, 64, 104, 63, 107, 46, 44, 45, 42, 13, 109, 14, 110, 96, 66, 65, 23, 20, 89, 61, 59, 49, 39, 38, 30, 21, 58, 53, 48, 94, 90, 60, 40, 37, 36, 33, 29, 76, 57, 54, 52, 31, 27, 26, 15, 93, 91, 85, 80, 75, 62, 32, 25, 24, 19, 18] },
	{ "s": "КНОПОК", "p": [71, 38, 95, 92, 75, 63, 30] },
	{ "s": "КО", "p": [111, 37, 36] },
	{ "s": "КОГДА", "p": [111, 78, 68, 63, 23, 16] },
	{ "s": "КОД", "p": [102, 99, 84] },
	{ "s": "КОДА", "p": [111, 102, 98, 4] },
	{ "s": "КОДЕ", "p": [100] },
	{ "s": "КОДИРОВАНИЯ", "p": [83] },
	{ "s": "КОДИРОВКУ", "p": [106] },
	{ "s": "КОДУ", "p": [31] },
	{ "s": "КОЛИЧЕСТВА", "p": [111, 89, 85, 23] },
	{ "s": "КОЛИЧЕСТВЕ", "p": [97] },
	{ "s": "КОЛИЧЕСТВО", "p": [58, 53, 100, 111, 96, 88, 84, 43, 112, 95, 80, 59, 21, 9, 8] },
	{ "s": "КОЛИЧЕСТВОМ", "p": [9] },
	{ "s": "КОЛОНКИ", "p": [59] },
	{ "s": "КОМАНДА", "p": [78] },
	{ "s": "КОМАНДНАЯ", "p": [51] },
	{ "s": "КОМАНДНОЙ", "p": [20] },
	{ "s": "КОМАНДНУЮ", "p": [78, 51] },
	{ "s": "КОМАНДУ", "p": [51] },
	{ "s": "КОМАНДЫ", "p": [32] },
	{ "s": "КОМБИНАЦИЮ", "p": [87, 71] },
	{ "s": "КОМБИНАЦИЯ", "p": [81] },
	{ "s": "КОММЕНТАРИЙ", "p": [84] },
	{ "s": "КОММЕНТАРИЯ", "p": [81] },
	{ "s": "КОММЕРЧЕСКУЮ", "p": [85] },
	{ "s": "КОМПАНИИ", "p": [72] },
	{ "s": "КОМПЛЕКС", "p": [3] },
	{ "s": "КОМПЛЕКТЕ", "p": [12] },
	{ "s": "КОМПОНЕНТ", "p": [10, 7, 11, 55, 13, 12, 3] },
	{ "s": "КОМПОНЕНТ(Ы", "p": [55] },
	{ "s": "КОМПОНЕНТАМ", "p": [51, 12] },
	{ "s": "КОМПОНЕНТАМИ", "p": [70, 7] },
	{ "s": "КОМПОНЕНТОВ", "p": [55, 26, 16, 15, 51, 84, 50, 19, 13, 12, 3] },
	{ "s": "КОМПОНЕНТЫ", "p": [50, 9, 78, 13, 12, 10, 8, 6, 3] },
	{ "s": "КОМПЬЮТЕР", "p": [32] },
	{ "s": "КОМПЬЮТЕРА", "p": [32] },
	{ "s": "КОМПЬЮТЕРАХ", "p": [32] },
	{ "s": "КОМПЬЮТЕРЕ", "p": [74, 20] },
	{ "s": "КОМУ", "p": [28] },
	{ "s": "КОМУ-ЛИБО", "p": [28] },
	{ "s": "КОНЕЦ", "p": [106] },
	{ "s": "КОНКРЕТНОГО", "p": [107, 94, 61, 25] },
	{ "s": "КОНКРЕТНОЙ", "p": [110, 83, 43] },
	{ "s": "КОНКРЕТНОМ", "p": [62] },
	{ "s": "КОНКРЕТНОМУ", "p": [107] },
	{ "s": "КОНКРЕТНУЮ", "p": [100, 99] },
	{ "s": "КОНКРЕТНЫМ", "p": [23] },
	{ "s": "КОНСОЛИ", "p": [32, 16, 12] },
	{ "s": "КОНСОЛЬ", "p": [12, 78, 51, 32] },
	{ "s": "КОНСУЛЬТАЦИЕЙ", "p": [10] },
	{ "s": "КОНСУЛЬТАЦИЯ", "p": [17] },
	{ "s": "КОНТАКТНЫЕ", "p": [30] },
	{ "s": "КОНТАКТЫ", "p": [30] },
	{ "s": "КОНТЕКСТНОГО", "p": [89, 65, 64, 46, 44, 31, 30] },
	{ "s": "КОНТЕКСТНОЕ", "p": [49, 105, 66, 65, 64, 48, 43, 39, 38] },
	{ "s": "КОНТЕКСТНОМ", "p": [90] },
	{ "s": "КОНТЕКСТНЫЙ", "p": [30, 46, 44] },
	{ "s": "КОНТЕКСТНЫМ", "p": [31, 29, 88, 64, 46, 44, 43, 30] },
	{ "s": "КОНТЕКСТНЫМ/РАСШИРЕННЫМ", "p": [29] },
	{ "s": "КОНТРОЛИРОВАТЬ", "p": [99, 28, 2] },
	{ "s": "КОНТРОЛИРУЕМЫМ", "p": [100, 25] },
	{ "s": "КОНТРОЛИРУЕТ", "p": [101, 98, 70, 2] },
	{ "s": "КОНТРОЛИРУЮТ", "p": [2] },
	{ "s": "КОНТРОЛЛЕР", "p": [73, 71] },
	{ "s": "КОНТРОЛЛЕРА", "p": [76, 32] },
	{ "s": "КОНТРОЛЬ", "p": [4, 2, 87, 109, 100, 107, 103, 102, 101] },
	{ "s": "КОНТРОЛЬНО", "p": [107, 27] },
	{ "s": "КОНТРОЛЬНО-ИЗМЕРИТЕЛЬНЫХ", "p": [27] },
	{ "s": "КОНТРОЛЬНОГО", "p": [100] },
	{ "s": "КОНТРОЛЮ", "p": [107, 103] },
	{ "s": "КОНТРОЛЯ", "p": [111, 87, 2] },
	{ "s": "КОНФИГУРАЦИИ", "p": [24, 40, 63, 23, 100, 92, 81, 25] },
	{ "s": "КОНФИГУРАЦИОННЫЙ", "p": [81] },
	{ "s": "КОНФИГУРАЦИЮ", "p": [24, 81, 80, 63, 40, 23] },
	{ "s": "КОНФИГУРАЦИЯ", "p": [13, 51, 14] },
	{ "s": "КОНЦА", "p": [36] },
	{ "s": "КОПИИ", "p": [16] },
	{ "s": "КОПИРОВАНИЯ", "p": [8] },
	{ "s": "КОПИЮ", "p": [16] },
	{ "s": "КОРНЕВОГО", "p": [32] },
	{ "s": "КОРНЕВОЙ", "p": [85] },
	{ "s": "КОРНЕВОМ", "p": [85] },
	{ "s": "КОРОБКИ", "p": [2] },
	{ "s": "КОРОТКИ", "p": [89] },
	{ "s": "КОРОТКИЕ", "p": [27] },
	{ "s": "КОРОТКИЙ", "p": [27] },
	{ "s": "КОРОТКИХ", "p": [27, 89] },
	{ "s": "КОРОТКОГО", "p": [27] },
	{ "s": "КОРОЧЕ", "p": [27] },
	{ "s": "КОРРЕКТИРОВКА", "p": [31, 89, 29] },
	{ "s": "КОРРЕКТИРОВКИ", "p": [100] },
	{ "s": "КОРРЕКТИРОВОК", "p": [89] },
	{ "s": "КОРРЕКТИРУЙТЕ", "p": [88, 43] },
	{ "s": "КОРРЕКТНО", "p": [102, 85, 51, 32, 28] },
	{ "s": "КОРРЕКТНОГО", "p": [106] },
	{ "s": "КОРРЕКТНОЕ", "p": [16] },
	{ "s": "КОРРЕКТНОЙ", "p": [93, 91, 90] },
	{ "s": "КОРРЕКТНОСТЬ", "p": [104, 83] },
	{ "s": "КОРРЕКТНЫЙ", "p": [50] },
	{ "s": "КОРРЕКЦИИ", "p": [97] },
	{ "s": "КОРРЕКЦИЯ", "p": [97] },
	{ "s": "КОСВЕННЫМ", "p": [77] },
	{ "s": "КОТОРАЯ", "p": [100, 106, 86, 70, 63] },
	{ "s": "КОТОРОГО", "p": [95, 63, 24] },
	{ "s": "КОТОРОЕ", "p": [102, 51, 27] },
	{ "s": "КОТОРОЙ", "p": [110, 109, 104, 100, 70] },
	{ "s": "КОТОРОМ", "p": [81, 32, 7] },
	{ "s": "КОТОРОМУ", "p": [36, 32, 31, 23] },
	{ "s": "КОТОРУЮ", "p": [107, 31] },
	{ "s": "КОТОРЫЕ", "p": [100, 86, 78, 111, 106, 99, 95, 92, 90, 85, 81, 77, 74, 60, 54, 43, 30, 13, 12, 8] },
	{ "s": "КОТОРЫЙ", "p": [27, 107, 13, 110, 96, 95, 81, 78, 77, 68, 60, 54, 42, 38, 26, 21, 20, 16] },
	{ "s": "КОТОРЫМ", "p": [81, 107, 78, 43, 37] },
	{ "s": "КОТОРЫХ", "p": [106, 95, 85, 35, 18] },
	{ "s": "КОЭФФИЦИЕНТА", "p": [103] },
	{ "s": "КРАЙ", "p": [36] },
	{ "s": "КРАСНЫЙ", "p": [89, 73] },
	{ "s": "КРАТНОМУ", "p": [36] },
	{ "s": "КРИТЕРИЕВ", "p": [103, 2] },
	{ "s": "КРИТИЧЕСКИ", "p": [60, 54] },
	{ "s": "КРИТИЧЕСКИЕ", "p": [102] },
	{ "s": "КРИТИЧЕСКИХ", "p": [4, 2] },
	{ "s": "КРОМЕ", "p": [102] },
	{ "s": "КРУГЛОСУТОЧНО", "p": [36] },
	{ "s": "КРУГОВАЯ", "p": [109] },
	{ "s": "КУДА", "p": [85] },
	{ "s": "КУРСОР", "p": [90] },
	{ "s": "КЭШ", "p": [10] }
]