[
	{ "s": "ЧАСОВ", "p": [36, 66] },
	{ "s": "ЧАСТИ", "p": [63, 101, 94, 83, 81, 61, 33, 26, 2] },
	{ "s": "ЧАСТНОМ", "p": [101, 97, 22] },
	{ "s": "ЧАСТО", "p": [59, 48] },
	{ "s": "ЧАСТОТА", "p": [9] },
	{ "s": "ЧАСТЬ", "p": [94, 62] },
	{ "s": "ЧАСЫ", "p": [66] },
	{ "s": "ЧЕГО", "p": [100, 75] },
	{ "s": "ЧЕКБОКСАХ", "p": [98] },
	{ "s": "ЧЕКБОКСЕ", "p": [40] },
	{ "s": "ЧЕМ", "p": [105, 94, 79, 27, 8] },
	{ "s": "ЧЕРЕЗ", "p": [23, 80, 79, 70, 49, 100, 99, 48, 38, 78, 75, 74, 73, 72, 66, 65, 64, 43, 39, 31, 27, 16, 12, 7] },
	{ "s": "ЧЕРНЫЙ", "p": [31] },
	{ "s": "ЧЕТНОЕ", "p": [9] },
	{ "s": "ЧЕТНОСТЬ", "p": [23] },
	{ "s": "ЧЕТЫРЕ", "p": [79, 78, 36, 29] },
	{ "s": "ЧИСЛА", "p": [58, 53, 105] },
	{ "s": "ЧИСЛЕ", "p": [106, 97, 58, 53, 2] },
	{ "s": "ЧИСЛО", "p": [58, 53, 106, 104, 94, 83, 49, 21] },
	{ "s": "ЧИТАТЬ", "p": [75] },
	{ "s": "ЧЛЕНСТВО", "p": [30, 29] },
	{ "s": "ЧЛЕНЫ", "p": [29] },
	{ "s": "ЧПУ", "p": [23, 101, 22, 10, 7, 2, 97, 88, 75, 63, 61, 60, 3] },
	{ "s": "ЧРЕЗВЫЧАЙНЫХ", "p": [2] },
	{ "s": "ЧТЕНИЕ", "p": [77, 31] },
	{ "s": "ЧТЕНИЯ", "p": [23, 8, 3] },
	{ "s": "ЧТО", "p": [12, 36, 51, 103, 94, 79, 73, 32, 105, 98, 87, 80, 75, 68, 63, 21, 20, 18, 17, 14, 13, 7] },
	{ "s": "ЧТОБЫ", "p": [91, 89, 99, 98, 101, 82, 43, 86, 42, 64, 63, 103, 90, 48, 40, 94, 88, 87, 84, 83, 75, 65, 59, 49, 46, 44, 39, 29, 104, 96, 85, 79, 76, 66, 62, 60, 58, 57, 53, 52, 45, 35, 30, 28, 14, 13] },
	{ "s": "ЧУВСТВИТЕЛЬНОЙ", "p": [79] }
]