[
	{ "s": "А", "p": [11, 72, 70, 69, 68, 65, 60, 59, 45, 35, 15] },
	{ "s": "АВАРИЙНЫЙ", "p": [31] },
	{ "s": "АВТОВРАЩЕНИЕ", "p": [59] },
	{ "s": "АВТОМАТИЗАЦИИ", "p": [56] },
	{ "s": "АВТОМАТИЗИРОВАННОГО", "p": [45] },
	{ "s": "АВТОМАТИЧЕСКИ", "p": [26, 22, 21] },
	{ "s": "АВТОМАТИЧЕСКОЙ", "p": [29] },
	{ "s": "АВТОМАТИЧЕСКОМ", "p": [29] },
	{ "s": "АВТОРИЗАЦИИ", "p": [24, 12, 40, 14] },
	{ "s": "АВТОРИЗАЦИИ/УПОЛНОМОЧЕННОГО", "p": [12] },
	{ "s": "АВТОРИЗАЦИЯ", "p": [24, 11] },
	{ "s": "АГЕНТА", "p": [52] },
	{ "s": "АГЕНТЫ", "p": [52] },
	{ "s": "АДМИНИСТРАТОРА", "p": [14, 40, 27, 11] },
	{ "s": "АДМИНИСТРАТОРОМ", "p": [42] },
	{ "s": "АДМИНИСТРАТОРЫ", "p": [41] },
	{ "s": "АДМИНИСТРИРОВАНИЕ", "p": [23, 42] },
	{ "s": "АДРЕС", "p": [27, 46, 29, 20, 19] },
	{ "s": "АДРЕСЕ", "p": [29] },
	{ "s": "АДРЕСУ", "p": [29] },
	{ "s": "АКТИВАЦИЕЙ", "p": [42] },
	{ "s": "АКТИВАЦИЯ", "p": [42] },
	{ "s": "АКТИВИРОВАН", "p": [40] },
	{ "s": "АКТИВНА", "p": [70, 69, 46] },
	{ "s": "АКТИВНОЙ", "p": [28] },
	{ "s": "АКТИВНЫЕ", "p": [53] },
	{ "s": "АКТИВНЫХ", "p": [53] },
	{ "s": "АКТУАЛЬНОЙ", "p": [4] },
	{ "s": "АКТУАЛЬНОСТЬ", "p": [27] },
	{ "s": "АКТУАЛЬНЫЙ", "p": [18] },
	{ "s": "АНАЛИТИК", "p": [72, 68, 65, 35] },
	{ "s": "АНАЛИТИКИ", "p": [35] },
	{ "s": "АНАЛОГИЧЕН", "p": [31] },
	{ "s": "АНАЛОГИЧНЫ", "p": [29] },
	{ "s": "АНАЛОГИЧНЫМ", "p": [72, 70, 69, 68, 65, 60, 59, 45, 35] },
	{ "s": "АРХИВНЫХ", "p": [30, 16] },
	{ "s": "АРХИТЕКТУРА", "p": [3] },
	{ "s": "АУТЕНТИФИКАЦИИ", "p": [42, 40] },
	{ "s": "АУТЕНТИФИКАЦИЯ", "p": [42] }
]