[
	{ "s": "C", "p": [32, 73, 26, 21, 16] },
	{ "s": "C:\\PROGRAM", "p": [32, 16] },
	{ "s": "CAPTURE", "p": [58, 53] },
	{ "s": "CD", "p": [73] },
	{ "s": "CE", "p": [5] },
	{ "s": "CERT", "p": [32] },
	{ "s": "CERT:\\LOCALMACHINE\\MY", "p": [32] },
	{ "s": "CERTHASH", "p": [32] },
	{ "s": "CERTSTORELOCATION", "p": [32] },
	{ "s": "CHAN2", "p": [68] },
	{ "s": "CHANGE", "p": [72, 73] },
	{ "s": "CHANGED", "p": [58, 53] },
	{ "s": "CIE", "p": [7] },
	{ "s": "CMD", "p": [73] },
	{ "s": "CNC", "p": [58, 53, 77] },
	{ "s": "COM", "p": [23, 98, 76, 73, 61, 55, 12, 7, 6] },
	{ "s": "COM-ПОРТ", "p": [23, 7] },
	{ "s": "COM-ПОРТОВ", "p": [23] },
	{ "s": "COMPANY", "p": [72] },
	{ "s": "CONFIG", "p": [16, 51] },
	{ "s": "CONTROLPROGRAMVERSIONTASKBASE", "p": [98] },
	{ "s": "CONTROLPROGRAMWITHOUTVERSIONBASE", "p": [98] },
	{ "s": "CONTROLPROGRAMWITHVERSIONBASE", "p": [98] },
	{ "s": "CREATE", "p": [98, 62, 32] },
	{ "s": "CREATECONTROLPROGRAMVERSION", "p": [98] },
	{ "s": "CREATECONTROLPROGRAMWITHOUTVERSION", "p": [98] },
	{ "s": "CREATECONTROLPROGRAMWITHVERSION", "p": [98] },
	{ "s": "CREATEORUPDATE", "p": [98] },
	{ "s": "CREATEORUPDATECONTROLPROGRAMVERSION", "p": [98] },
	{ "s": "CREATEORUPDATECONTROLPROGRAMWITHOUTVERSION", "p": [98] },
	{ "s": "CUSTOMER", "p": [72] }
]