[
	{ "s": "В", "p": [86, 81, 26, 41, 31, 38, 44, 40, 72, 35, 79, 21, 87, 70, 56, 93, 47, 52, 36, 24, 65, 3, 68, 60, 28, 25, 22, 76, 66, 89, 64, 39, 61, 74, 45, 5, 90, 73, 62, 51, 50, 37, 67, 42, 33, 29, 15, 94, 92, 91, 46, 34, 19, 18, 10, 75, 71, 69, 20, 14, 88, 82, 78, 77, 23, 11, 85, 83, 80, 58, 55, 54, 53, 43, 30, 16, 8, 6, 4, 57, 48, 17, 13, 9] },
	{ "s": "ВАЛИДАЦИЯ", "p": [19] },
	{ "s": "ВАМ", "p": [52, 13, 75, 51, 40] },
	{ "s": "ВАМИ", "p": [79, 51] },
	{ "s": "ВАРИАНТ", "p": [37] },
	{ "s": "ВАРИАНТА", "p": [13, 9] },
	{ "s": "ВАРИАНТОВ", "p": [77, 74, 65, 61, 60, 41, 36, 24, 21] },
	{ "s": "ВАРИАНТЫ", "p": [9, 58, 52, 26] },
	{ "s": "ВАС", "p": [52, 89, 77, 53] },
	{ "s": "ВАШЕМ", "p": [50] },
	{ "s": "ВВЕДЁННЫЕ", "p": [85, 80] },
	{ "s": "ВВЕДЕНА", "p": [47] },
	{ "s": "ВВЕДЕННОЙ", "p": [77] },
	{ "s": "ВВЕДЕННЫЕ", "p": [38, 70, 36] },
	{ "s": "ВВЕДЕННЫХ", "p": [76, 35, 24] },
	{ "s": "ВВЕДИТЕ", "p": [41, 70, 65, 44, 29, 72, 68, 67, 66, 57, 54, 52, 38, 36, 24, 21] },
	{ "s": "ВВОД", "p": [38, 40, 34, 25] },
	{ "s": "ВВОДА", "p": [41, 69, 38, 25, 20] },
	{ "s": "ВВОДИТЬ", "p": [72, 70, 68, 66, 41] },
	{ "s": "ВЕБ", "p": [66, 72, 68, 67, 46, 44] },
	{ "s": "ВЕБ-УВЕДОМЛЕНИЕ", "p": [66, 68, 44] },
	{ "s": "ВЕБ-УВЕДОМЛЕНИЙ", "p": [66, 72] },
	{ "s": "ВЕБ-УВЕДОМЛЕНИЯ", "p": [66, 72, 67, 68] },
	{ "s": "ВЕДЁТСЯ", "p": [31] },
	{ "s": "ВЕДЕНИЕ", "p": [32] },
	{ "s": "ВЕДЕНИЯ", "p": [91] },
	{ "s": "ВЕДЕТ", "p": [53] },
	{ "s": "ВЕДЕТСЯ", "p": [38, 33] },
	{ "s": "ВЕЛИЧИНА", "p": [86, 81, 40] },
	{ "s": "ВЕРИФИКАЦИИ", "p": [31] },
	{ "s": "ВЕРИФИКАЦИЯ", "p": [34] },
	{ "s": "ВЕРИФИЦИРОВАННЫХ", "p": [31] },
	{ "s": "ВЕРНУТЬСЯ", "p": [40] },
	{ "s": "ВЕРНЫ", "p": [15] },
	{ "s": "ВЕРОЯТНОСТНАЯ", "p": [38] },
	{ "s": "ВЕРСИЕЙ", "p": [37] },
	{ "s": "ВЕРСИИ", "p": [36, 92, 83, 37, 78, 38, 26, 7, 6, 3] },
	{ "s": "ВЕРСИЙ", "p": [38] },
	{ "s": "ВЕРСИННОЕ", "p": [36] },
	{ "s": "ВЕРСИОННОСТИ", "p": [36, 32] },
	{ "s": "ВЕРСИОННОСТЬ", "p": [30, 5] },
	{ "s": "ВЕРСИЮ", "p": [37, 36, 89, 15] },
	{ "s": "ВЕРСИЯ", "p": [92, 89, 16, 51, 36, 33, 17, 15, 5] },
	{ "s": "ВЕРТИКАЛЬНАЯ", "p": [28] },
	{ "s": "ВЕРХНЕГО", "p": [72] },
	{ "s": "ВЕРХНЕЙ", "p": [38] },
	{ "s": "ВЕРХНЕМ", "p": [71, 70, 65, 52, 44, 29] },
	{ "s": "ВЕСТИ", "p": [69, 33, 30] },
	{ "s": "ВЗАИМОДЕЙСТВИЕ", "p": [91] },
	{ "s": "ВЗАИМОДЕЙСТВИЯ", "p": [90, 4] },
	{ "s": "ВЗАИМОДЕЙСТВОВАТЬ", "p": [3] },
	{ "s": "ВЗЯТА", "p": [31] },
	{ "s": "ВИБРАЦИЙ", "p": [5] },
	{ "s": "ВИБРОМОНИТОРИНГА", "p": [54, 56] },
	{ "s": "ВИД", "p": [65, 41, 29] },
	{ "s": "ВИДА", "p": [79, 35, 18] },
	{ "s": "ВИДАХ", "p": [25, 28, 23] },
	{ "s": "ВИДЕ", "p": [38, 22, 94, 93, 40, 33, 31, 30, 26, 3] },
	{ "s": "ВИДЕТЬ", "p": [33] },
	{ "s": "ВИДЖЕТ", "p": [65, 29] },
	{ "s": "ВИДЖЕТА", "p": [65, 29, 35, 25] },
	{ "s": "ВИДЖЕТОВ", "p": [65, 29, 35, 25] },
	{ "s": "ВИДЖЕТОМ", "p": [65, 29] },
	{ "s": "ВИДЖЕТЫ", "p": [65, 29] },
	{ "s": "ВИДИМ", "p": [73] },
	{ "s": "ВИДИМЫМ", "p": [41] },
	{ "s": "ВИДОВ", "p": [25] },
	{ "s": "ВИЗУАЛИЗАЦИИ", "p": [22, 28, 25] },
	{ "s": "ВИЗУАЛИЗАЦИЯ", "p": [5] },
	{ "s": "ВИЗУАЛИЗИРОВАН", "p": [40] },
	{ "s": "ВИРТУАЛЬНЫЕ", "p": [47] },
	{ "s": "ВИРТУАЛЬНЫЙ", "p": [15, 4] },
	{ "s": "ВИРТУАЛЬНЫХ", "p": [47] },
	{ "s": "ВКЛАДКА", "p": [70] },
	{ "s": "ВКЛАДКАМ", "p": [35, 25] },
	{ "s": "ВКЛАДКЕ", "p": [70, 71, 72, 59, 40, 38, 23] },
	{ "s": "ВКЛАДКИ", "p": [38] },
	{ "s": "ВКЛАДКУ", "p": [35, 89, 88, 86, 84, 83, 82, 81, 74, 72, 71, 70, 65, 54, 36, 29] },
	{ "s": "ВКЛЮЧАЕТ", "p": [52, 33] },
	{ "s": "ВКЛЮЧАТЬ", "p": [91, 60, 58] },
	{ "s": "ВКЛЮЧАЮЩЕЙ", "p": [93] },
	{ "s": "ВКЛЮЧАЮЩИЙ", "p": [4] },
	{ "s": "ВКЛЮЧАЯ", "p": [93] },
	{ "s": "ВКЛЮЧЕН", "p": [78, 70] },
	{ "s": "ВКЛЮЧЕННОМ", "p": [89] },
	{ "s": "ВКЛЮЧЕННЫЙ", "p": [89] },
	{ "s": "ВКЛЮЧЕННЫХ", "p": [74] },
	{ "s": "ВКЛЮЧЕНЫ", "p": [72] },
	{ "s": "ВЛИЯЕТ", "p": [11] },
	{ "s": "ВЛИЯНИЕ", "p": [19] },
	{ "s": "ВЛОЖЕНИЙ", "p": [3] },
	{ "s": "ВЛОЖЕНИЯМИ", "p": [44] },
	{ "s": "ВЛОЖЕННОСТИ", "p": [38] },
	{ "s": "ВМЕСТЕ", "p": [93] },
	{ "s": "ВМЕСТО", "p": [94, 93, 79] },
	{ "s": "ВНЕДРЕНИЯ", "p": [93, 45, 3] },
	{ "s": "ВНЕДРЕННЫЕ", "p": [93] },
	{ "s": "ВНЕСЁННЫЕ", "p": [31] },
	{ "s": "ВНЕСЕН", "p": [72] },
	{ "s": "ВНЕСЕННЫЕ", "p": [44, 87, 58, 31, 25] },
	{ "s": "ВНЕСЕННЫМ", "p": [36] },
	{ "s": "ВНЕСЕННЫХ", "p": [36, 31] },
	{ "s": "ВНЕСЕНЫ", "p": [72] },
	{ "s": "ВНЕСТИ", "p": [45, 15] },
	{ "s": "ВНЕШНЕЙ", "p": [92] },
	{ "s": "ВНЕШНИЕ", "p": [93, 88, 82, 56, 39] },
	{ "s": "ВНИМАНИЕ", "p": [14, 50, 45, 18, 9] },
	{ "s": "ВНИМАТЕЛЬНО", "p": [16, 15] },
	{ "s": "ВНОВЬ", "p": [72, 70, 57, 15] },
	{ "s": "ВНУТРИ", "p": [74, 34] },
	{ "s": "ВО", "p": [74, 93, 72, 35, 25, 8, 3] },
	{ "s": "ВОЗВЕДИТЕ", "p": [39, 65, 38, 29] },
	{ "s": "ВОЗВРАТ", "p": [40] },
	{ "s": "ВОЗВРАЩАЕТ", "p": [40] },
	{ "s": "ВОЗМОЖНА", "p": [18] },
	{ "s": "ВОЗМОЖНО", "p": [93, 58, 51] },
	{ "s": "ВОЗМОЖНОГО", "p": [56] },
	{ "s": "ВОЗМОЖНОСТЕЙ", "p": [69] },
	{ "s": "ВОЗМОЖНОСТИ", "p": [56, 3, 94, 93, 19] },
	{ "s": "ВОЗМОЖНОСТЬ", "p": [72, 56, 5, 38, 35, 25, 93, 90, 54, 42, 40, 39, 32, 31] },
	{ "s": "ВОЗМОЖНОСТЬЮ", "p": [36] },
	{ "s": "ВОЗМОЖНЫ", "p": [38] },
	{ "s": "ВОЗМОЖНЫЕ", "p": [78, 52, 45] },
	{ "s": "ВОЗМОЖНЫХ", "p": [45] },
	{ "s": "ВОЗНИКЛА", "p": [93, 37] },
	{ "s": "ВОЗНИКЛИ", "p": [79] },
	{ "s": "ВОЗНИКНОВЕНИИ", "p": [78, 20, 18] },
	{ "s": "ВОЗНИКНОВЕНИЯ", "p": [44, 43, 35, 31, 25] },
	{ "s": "ВОЗНИКНУТЬ", "p": [83] },
	{ "s": "ВОКРУГ", "p": [60] },
	{ "s": "ВОПРОСОВ", "p": [18, 2] },
	{ "s": "ВОПРОСЫ", "p": [93] },
	{ "s": "ВОСЕМЬЮ", "p": [65, 29] },
	{ "s": "ВОСПОЛЬЗОВАВШИСЬ", "p": [72] },
	{ "s": "ВОСПОЛЬЗОВАЛИСЬ", "p": [69] },
	{ "s": "ВОСПОЛЬЗОВАТЬСЯ", "p": [71, 72, 70, 68, 66, 41, 35, 31] },
	{ "s": "ВОСПОЛЬЗУЙТЕСЬ", "p": [38, 25, 75, 70, 65, 46, 44, 39, 35, 29, 13] },
	{ "s": "ВОССТАНОВИТЬ", "p": [53] },
	{ "s": "ВОССТАНОВИТЬ/ОБНОВИТЬ", "p": [53] },
	{ "s": "ВОССТАНОВЛЕНИЯ", "p": [18, 5] },
	{ "s": "ВОТ", "p": [74] },
	{ "s": "ВРАЩЕНИЯ", "p": [60, 26] },
	{ "s": "ВРЕМЕНИ", "p": [31, 3, 87, 40, 91, 76, 75, 44, 28, 4, 38, 35, 34, 26, 25, 19, 5] },
	{ "s": "ВРЕМЕННОЙ", "p": [28] },
	{ "s": "ВРЕМЕННЫЕ", "p": [38, 11] },
	{ "s": "ВРЕМЕННЫМ", "p": [58] },
	{ "s": "ВРЕМЕННЫХ", "p": [58, 3] },
	{ "s": "ВРЕМЯ", "p": [26, 58, 44, 92, 35, 31, 93, 86, 81, 77, 69, 56, 43, 40, 39, 38, 34, 33, 25, 18, 8, 3] },
	{ "s": "ВРЕМЯ/С", "p": [44] },
	{ "s": "ВРУЧНУЮ", "p": [82, 52, 88] },
	{ "s": "ВСЁ", "p": [10] },
	{ "s": "ВСЕ", "p": [94, 44, 93, 75, 74, 68, 66, 56, 38, 36, 35, 15, 79, 78, 76, 73, 72, 70, 67, 60, 42, 41, 40, 25, 14, 9] },
	{ "s": "ВСЕГДА", "p": [74, 38] },
	{ "s": "ВСЕМ", "p": [59, 42] },
	{ "s": "ВСЕМИ", "p": [17] },
	{ "s": "ВСЕХ", "p": [88, 82, 74, 65, 29, 72, 69, 59, 38, 35, 15, 11] },
	{ "s": "ВСПЛЫВАЮЩЕГО", "p": [40] },
	{ "s": "ВСПЛЫВАЮЩЕЕ", "p": [35] },
	{ "s": "ВСПЛЫВАЮЩЕЙ", "p": [25] },
	{ "s": "ВСПЛЫВАЮЩЕМ", "p": [25] },
	{ "s": "ВСПЛЫВАЮЩИЕ", "p": [25] },
	{ "s": "ВСПОМОГАТЕЛЬНЫМ", "p": [41] },
	{ "s": "ВСТАВИТЬ", "p": [73] },
	{ "s": "ВСТАНЬТЕ", "p": [57] },
	{ "s": "ВСТРОЕННАЯ", "p": [14, 3] },
	{ "s": "ВСТРОЕННЫЕ", "p": [14, 91] },
	{ "s": "ВСЯ", "p": [47, 36] },
	{ "s": "ВТОРОМ", "p": [93] },
	{ "s": "ВХОД", "p": [72, 79] },
	{ "s": "ВХОДА", "p": [70, 69, 73, 54] },
	{ "s": "ВХОДЕ", "p": [72, 70, 46] },
	{ "s": "ВХОДНЫМИ", "p": [65] },
	{ "s": "ВХОДНЫХ", "p": [65] },
	{ "s": "ВХОДОВ", "p": [54] },
	{ "s": "ВХОДОВ/ВЫХОДОВ", "p": [54] },
	{ "s": "ВХОДЯЩЕГО", "p": [92] },
	{ "s": "ВХОДЯЩИЕ", "p": [93] },
	{ "s": "ВХОДЯЩИХ", "p": [56] },
	{ "s": "ВХОДЯЩИХ/ИСХОДЯЩИХ", "p": [56] },
	{ "s": "ВЫ", "p": [71, 70, 15, 41, 57, 50, 21, 87, 72, 69, 52, 46, 40, 19, 17, 16] },
	{ "s": "ВЫБЕРЕТЕ", "p": [23] },
	{ "s": "ВЫБЕРИТЕ", "p": [26, 44, 65, 38, 47, 25, 40, 36, 29, 41, 39, 28, 89, 77, 64, 60, 35, 22, 20, 87, 72, 70, 68, 66, 61, 52, 24, 21, 88, 76, 71, 59, 58, 57, 55, 53, 43, 42, 16, 15, 93, 86, 85, 84, 83, 82, 81, 80, 73, 67, 56, 50, 49, 48, 31, 18] },
	{ "s": "ВЫБИРАЕТ", "p": [49] },
	{ "s": "ВЫБИРАЕТСЯ", "p": [91] },
	{ "s": "ВЫБИРАТЬ", "p": [49] },
	{ "s": "ВЫБОР", "p": [65, 29, 86, 81, 41, 87, 47, 89, 35, 15, 68, 67, 66, 59, 52, 44, 40, 36, 20, 17, 3] },
	{ "s": "ВЫБОРА", "p": [56, 58, 86, 81, 62, 38, 36, 15] },
	{ "s": "ВЫБОРЕ", "p": [50, 87, 65, 52, 29, 9] },
	{ "s": "ВЫБОРНЫМИ", "p": [79] },
	{ "s": "ВЫБОРУ", "p": [15] },
	{ "s": "ВЫБРАЛИ", "p": [46] },
	{ "s": "ВЫБРАН", "p": [70, 44] },
	{ "s": "ВЫБРАНА", "p": [91] },
	{ "s": "ВЫБРАННАЯ", "p": [51] },
	{ "s": "ВЫБРАННОГО", "p": [26, 72, 70, 68, 66, 47, 35, 34, 25, 22, 13] },
	{ "s": "ВЫБРАННОЕ", "p": [25] },
	{ "s": "ВЫБРАННОЙ", "p": [25, 71, 35] },
	{ "s": "ВЫБРАННОМ", "p": [26, 35] },
	{ "s": "ВЫБРАННОМУ", "p": [72, 56, 65, 61, 60, 59, 41, 36, 26, 24, 23, 22, 21] },
	{ "s": "ВЫБРАННУЮ", "p": [20] },
	{ "s": "ВЫБРАННЫЕ", "p": [26, 44, 28, 15, 64, 35, 22] },
	{ "s": "ВЫБРАННЫЙ", "p": [79, 28, 25, 40, 38, 35, 31, 16, 15] },
	{ "s": "ВЫБРАННЫМ", "p": [5] },
	{ "s": "ВЫБРАННЫХ", "p": [79, 65, 61, 29, 25] },
	{ "s": "ВЫБРАНЫ", "p": [77, 35] },
	{ "s": "ВЫБРАТЬ", "p": [74, 47, 35, 62, 41, 15, 87, 86, 85, 81, 80, 76, 70, 44, 37, 36, 33, 19] },
	{ "s": "ВЫБРОМОНИТОРИНГА", "p": [56] },
	{ "s": "ВЫВЕДЕНО", "p": [25] },
	{ "s": "ВЫВЕДЕНЫ", "p": [42, 31] },
	{ "s": "ВЫВЕРЕННОЙ", "p": [31] },
	{ "s": "ВЫВОДА", "p": [56, 43, 38] },
	{ "s": "ВЫГОДНО", "p": [9] },
	{ "s": "ВЫГОДЫ", "p": [3] },
	{ "s": "ВЫГРУЗКА", "p": [56] },
	{ "s": "ВЫГРУЗКИ", "p": [56, 93, 39, 45, 5] },
	{ "s": "ВЫДАЕТ", "p": [3] },
	{ "s": "ВЫДАЧА", "p": [54, 31] },
	{ "s": "ВЫДЕЛЕННОМ", "p": [93] },
	{ "s": "ВЫДЕЛЕННЫХ", "p": [9] },
	{ "s": "ВЫДЕЛЕНЫ", "p": [31] },
	{ "s": "ВЫДЕЛИТЬ", "p": [73, 11] },
	{ "s": "ВЫДЕРЖКИ", "p": [47] },
	{ "s": "ВЫЗВАНЫ", "p": [65, 36, 77, 61, 60, 41, 24, 21] },
	{ "s": "ВЫЗВАТЬ", "p": [94] },
	{ "s": "ВЫЗОВ", "p": [37] },
	{ "s": "ВЫЗОВА", "p": [94, 45] },
	{ "s": "ВЫЗОВИТЕ", "p": [79, 52] },
	{ "s": "ВЫЗЫВАЕМОГО", "p": [40] },
	{ "s": "ВЫЗЫВАЕТ", "p": [36] },
	{ "s": "ВЫЗЫВАТЬСЯ", "p": [65] },
	{ "s": "ВЫЗЫВАЮЩАЯ", "p": [37] },
	{ "s": "ВЫНЕСЕН", "p": [13] },
	{ "s": "ВЫПАДАЮЩЕГО", "p": [65, 47, 39, 36, 29, 93, 85, 80, 76, 73, 72, 71, 70, 68, 67, 66, 64, 57, 55, 48, 44, 40, 26, 22, 16, 15] },
	{ "s": "ВЫПАДАЮЩЕМ", "p": [26, 44, 28, 40, 22, 65, 41, 39, 29, 20, 89, 88, 87, 72, 70, 68, 66, 64, 61, 60, 56, 52, 47, 42, 38, 36, 35, 34, 25, 24, 21] },
	{ "s": "ВЫПАДАЮЩИЕ", "p": [44] },
	{ "s": "ВЫПАДАЮЩИХ", "p": [44, 35] },
	{ "s": "ВЫПОЛНЕН", "p": [62, 47, 40, 38] },
	{ "s": "ВЫПОЛНЕНА", "p": [44] },
	{ "s": "ВЫПОЛНЕНИЕ", "p": [38, 34, 31, 3] },
	{ "s": "ВЫПОЛНЕНИЕМ", "p": [5] },
	{ "s": "ВЫПОЛНЕНИИ", "p": [56, 49, 44] },
	{ "s": "ВЫПОЛНЕНИЯ", "p": [26, 38, 93, 25, 92, 91, 56, 40, 34, 31, 3] },
	{ "s": "ВЫПОЛНЕННОГО", "p": [33, 5] },
	{ "s": "ВЫПОЛНЕННЫЙ", "p": [40] },
	{ "s": "ВЫПОЛНЕННЫХ", "p": [31] },
	{ "s": "ВЫПОЛНЕНО", "p": [89, 38] },
	{ "s": "ВЫПОЛНЕНЫ", "p": [44, 14] },
	{ "s": "ВЫПОЛНИТЕ", "p": [26, 72, 65, 61, 60, 44, 41, 36, 25, 24, 21, 79, 77, 57, 53, 35, 18] },
	{ "s": "ВЫПОЛНИТЬ", "p": [79, 94, 93, 74, 70, 53, 40] },
	{ "s": "ВЫПОЛНЯЕМАЯ", "p": [38, 34] },
	{ "s": "ВЫПОЛНЯЕМОЙ", "p": [35, 25] },
	{ "s": "ВЫПОЛНЯЕТСЯ", "p": [79] },
	{ "s": "ВЫПОЛНЯЛАСЬ", "p": [31] },
	{ "s": "ВЫПОЛНЯЛИСЬ", "p": [73, 30] },
	{ "s": "ВЫПОЛНЯЮТ", "p": [91] },
	{ "s": "ВЫПОЛНЯЮТСЯ", "p": [94] },
	{ "s": "ВЫПОЛНЯЮЩУЮ", "p": [32] },
	{ "s": "ВЫПОЛНЯЮЩУЮСЯ", "p": [30] },
	{ "s": "ВЫПУСК", "p": [31, 56] },
	{ "s": "ВЫПУСКА", "p": [26, 40] },
	{ "s": "ВЫПУСКАЕМЫХ", "p": [92] },
	{ "s": "ВЫПУСКЕ", "p": [56] },
	{ "s": "ВЫПУСКУ", "p": [40] },
	{ "s": "ВЫПУЩЕННОЙ", "p": [40] },
	{ "s": "ВЫПУЩЕННЫХ", "p": [40, 26] },
	{ "s": "ВЫПУЩЕНО", "p": [53] },
	{ "s": "ВЫРАБОТКИ", "p": [5, 3] },
	{ "s": "ВЫСОКИМИ", "p": [14] },
	{ "s": "ВЫСОКИХ", "p": [88, 82] },
	{ "s": "ВЫСТАВИТЕ", "p": [44] },
	{ "s": "ВЫСТАВИТЬ", "p": [62] },
	{ "s": "ВЫСТАВЛЕН", "p": [88, 82] },
	{ "s": "ВЫСТАВЛЕНИЯ", "p": [60] },
	{ "s": "ВЫСТАВЛЯЕМЫЙ", "p": [22] },
	{ "s": "ВЫСТАВЬТЕ", "p": [61] },
	{ "s": "ВЫХОДА", "p": [54] },
	{ "s": "ВЫХОДОВ", "p": [54] },
	{ "s": "ВЫЧИСЛЕНИЯ", "p": [88, 82] },
	{ "s": "ВЫЧИТЫВАНИЕ", "p": [5] },
	{ "s": "ВЫШЕ", "p": [52, 6] },
	{ "s": "ВЫШЕЛ", "p": [91] },
	{ "s": "ВЫЯВИТЬ", "p": [93] }
]