[
	{ "s": "ЦВЕТ", "p": [29] },
	{ "s": "ЦВЕТА", "p": [27, 16] },
	{ "s": "ЦВЕТОМ", "p": [31] },
	{ "s": "ЦЕЛЕВОЙ", "p": [29] },
	{ "s": "ЦЕЛЕВОМ", "p": [16] },
	{ "s": "ЦЕЛЕВЫЕ", "p": [30] },
	{ "s": "ЦЕЛЕЙ", "p": [63] },
	{ "s": "ЦЕЛОМ", "p": [27] },
	{ "s": "ЦЕЛЯМИ", "p": [2] },
	{ "s": "ЦЕЛЯХ", "p": [4] },
	{ "s": "ЦЕНТР", "p": [42, 30, 59, 52, 36, 29, 28, 23] },
	{ "s": "ЦЕНТРА", "p": [54, 52, 30, 29, 17, 16] },
	{ "s": "ЦЕНТРАЛИЗОВАННОЕ", "p": [26] },
	{ "s": "ЦЕНТРАХ", "p": [27, 24] },
	{ "s": "ЦЕНТРЕ", "p": [27] },
	{ "s": "ЦЕНТРОВ", "p": [56, 68, 45, 33, 22] },
	{ "s": "ЦЕНТРУ", "p": [14] },
	{ "s": "ЦЕНТРЫ", "p": [33, 56, 27, 30, 29, 2] },
	{ "s": "ЦЕХ", "p": [36, 52, 42] },
	{ "s": "ЦЕХА", "p": [4] },
	{ "s": "ЦЕХОВ", "p": [8] },
	{ "s": "ЦЕХОВАЯ", "p": [11] },
	{ "s": "ЦЕХУ", "p": [4] },
	{ "s": "ЦИКЛ", "p": [51, 29] },
	{ "s": "ЦИКЛА", "p": [29, 51, 27] },
	{ "s": "ЦИКЛОВ", "p": [80, 75] },
	{ "s": "ЦИКЛУ", "p": [29] },
	{ "s": "ЦИКЛЫ", "p": [31] },
	{ "s": "ЦИФРОВОГО", "p": [49, 2] },
	{ "s": "ЦИФРОВОЕ", "p": [2] },
	{ "s": "ЦИФРОВОМ", "p": [24] },
	{ "s": "ЦИФРОВЫХ", "p": [49, 2] },
	{ "s": "ЦИФРЫ", "p": [66] }
]