{
	"1": ["DPA", "index.htm"],
	"2": ["О системе", "o_sisteme.htm"],
	"3": ["Архитектура системы", "arkhitektura_sistemy.htm"],
	"4": ["Поддерживаемые СУБД", "podderzhivaemye_subd.htm"],
	"5": ["Сеть и маршрутизация", "set_i_marshrutizatsiya.htm"],
	"6": ["Варианты развертывания", "varianty_razvertyvaniya.htm"],
	"7": ["DEMO", "demo.htm"],
	"8": ["Малые проекты", "malye_proekty.htm"],
	"9": ["Крупные проекты и масштабирование", "krupnye_proekty_i_masshtabirovanie.htm"],
	"10": ["4.4", "4_4.htm"],
	"11": ["Установка", "ustanovka.htm"],
	"12": ["Подготовка сервера к установке", "podgotovka_servera_k_ustanovke.htm"],
	"13": ["Установка DPA", "ustanovka_dpa.htm"],
	"14": ["Установка DPA Server ", "ustanovka_dpa_server_.htm"],
	"15": ["Обновление компонентов: DPA Server и DPA Host", "obnovlenie_komponentov__dpa_server_i_dpa_host.htm"],
	"16": ["Обновление конфигурации и настроек логирования драйвера", "obnovlenie_konfiguratsii_i_nastroek_logirovaniya_drajvera_1.htm"],
	"17": ["Перенос компонентов системы на другой сервер ", "perenos_komponentov_sistemy_na_drugoj_server_.htm"],
	"18": ["Администрирование", "administrirovanie.htm"],
	"19": ["Первый запуск и авторизация", "pervyj_zapusk_i_avtorizatsiya.htm"],
	"20": ["Первичная настройка системы", "pervichnaya_nastrojka_sistemy.htm"],
	"21": ["Настройка мониторинга", "nastrojka_monitoringa.htm"],
	"22": ["Добавление сервера и транспорта", "dobavlenie_servera_i_transporta.htm"],
	"23": ["Получение лицензии", "poluchenie_litsenzii.htm"],
	"24": ["Создание драйвера", "sozdanie_drajvera.htm"],
	"25": ["Обновление конфигурации и настроек логирования драйвера", "obnovlenie_konfiguratsii_i_nastroek_logirovaniya_drajvera_2.htm"],
	"26": ["Устройства вибромониторинга ", "ustrojstva_vibromonitoringa_.htm"],
	"27": ["Загрузка установочных компонентов системы", "zagruzka_ustanovochnykh_komponentov_sistemy.htm"],
	"28": ["Конфигурирование экранных и отчетных форм", "konfigurirovanie_ehkrannykh_i_otchetnykh_form.htm"],
	"29": ["Шаблоны отчетов Excel", "shablony_otchetov_excel.htm"],
	"30": ["Настройка приборных панелей", "nastrojka_pribornykh_panelej.htm"],
	"31": ["Настройка отправки веб-уведомлений", "nastrojka_otpravki_veb_uvedomlenij.htm"],
	"32": ["Настройка отправки электронной почты", "nastrojka_otpravki_ehlektronnoj_pochty.htm"],
	"33": ["Настройка отправки СМС", "nastrojka_otpravki_sms.htm"],
	"34": ["Настройки безопасности", "nastrojki_bezopasnosti.htm"],
	"35": ["Пользователи. Создание, редактирование и удаление учетной записи пользователя", "polzovateli__sozdanie__redaktirovanie_i_udalenie_uchetnoj_zapisi_polzovatelya.htm"],
	"36": ["Группы. Создание, редактирование и удаление группы доступа", "gruppy__sozdanie__redaktirovanie_i_udalenie_gruppy_dostupa.htm"],
	"37": ["Настройка прав доступа", "nastrojka_prav_dostupa.htm"],
	"38": ["Настройка хранения данных", "nastrojka_khraneniya_dannykh.htm"],
	"39": ["Индикаторы", "indikatory.htm"],
	"40": ["Очистка журналов", "ochistka_zhurnalov.htm"],
	"41": ["Возможные проблемы", "vozmozhnye_problemy.htm"],
	"42": ["Общая диагностика", "obshchaya_diagnostika.htm"],
	"43": ["Сервер", "server.htm"],
	"44": ["Счетчики производительности", "schetchiki_proizvoditelnosti_1.htm"],
	"45": ["Журналы", "zhurnaly_1.htm"],
	"46": ["Совместимость", "sovmestimost.htm"],
	"47": ["Диагностика", "diagnostika.htm"],
	"48": ["Драйверы", "drajvery.htm"],
	"49": ["Счетчики производительности", "schetchiki_proizvoditelnosti_2.htm"],
	"50": ["Снижение нагрузки", "snizhenie_nagruzki.htm"],
	"51": ["Журналы", "zhurnaly_2.htm"],
	"52": ["Агент", "agent.htm"],
	"53": ["Базовая настройка", "bazovaya_nastrojka.htm"],
	"54": ["Структура предприятия", "struktura_predpriyatiya.htm"],
	"55": ["Рабочее время", "rabochee_vremya.htm"],
	"56": ["Безопасность", "bezopasnost.htm"],
	"57": ["3D–модели оборудования", "3d_modeli_oborudovaniya.htm"],
	"58": ["Группы рабочих центров", "gruppy_rabochikh_tsentrov.htm"],
	"59": ["Настройки системы", "nastrojki_sistemy.htm"],
	"60": ["Интеграция", "integratsiya.htm"],
	"61": ["Настройка интеграции", "nastrojka_integratsii.htm"],
	"62": ["Сценарии использования", "stsenarii_ispolzovaniya.htm"],
	"63": ["Базовый мониторинг", "bazovyj_monitoring.htm"],
	"64": ["Справочники", "spravochniki_1.htm"],
	"65": ["Аналитика", "analitika_1.htm"],
	"66": ["Журналы", "zhurnaly_3.htm"],
	"67": ["Классификация простоев", "klassifikatsiya_prostoev.htm"],
	"68": ["Справочники", "spravochniki_2.htm"],
	"69": ["Аналитика", "analitika_2.htm"],
	"70": ["Контроль загрузки оборудования", "kontrol_zagruzki_oborudovaniya.htm"],
	"71": ["Работа с управляющими программами", "rabota_s_upravlyayushchimi_programmami.htm"],
	"72": ["Технология", "tekhnologiya.htm"],
	"73": ["Сменно-суточные задания", "smenno_sutochnye_zadaniya.htm"],
	"74": ["Оператор", "operator.htm"],
	"75": ["Диспетчерский пульт", "dispetcherskij_pult.htm"],
	"76": ["Сигналы", "signaly.htm"]
}