[
	{ "s": "ЧАСОВ", "p": [62] },
	{ "s": "ЧАСТИ", "p": [59, 90, 83, 72, 70, 57] },
	{ "s": "ЧАСТНОМ", "p": [90, 86] },
	{ "s": "ЧАСТО", "p": [55] },
	{ "s": "ЧАСТЬ", "p": [83, 58] },
	{ "s": "ЧАСЫ", "p": [62] },
	{ "s": "ЧЕГО", "p": [89] },
	{ "s": "ЧЕКБОКСАХ", "p": [87] },
	{ "s": "ЧЕМ", "p": [83, 68] },
	{ "s": "ЧЕРЕЗ", "p": [69, 68, 89, 88, 64, 67, 63, 62, 61, 60, 27] },
	{ "s": "ЧЕТЫРЕ", "p": [68, 67] },
	{ "s": "ЧИСЛА", "p": [54, 49] },
	{ "s": "ЧИСЛЕ", "p": [86, 54, 49] },
	{ "s": "ЧИСЛО", "p": [54, 49, 93, 83, 72] },
	{ "s": "ЧПУ", "p": [90, 86, 77, 59, 57, 56] },
	{ "s": "ЧТЕНИЕ", "p": [66] },
	{ "s": "ЧТО", "p": [92, 83, 68, 87, 76, 69, 59] },
	{ "s": "ЧТОБЫ", "p": [80, 78, 88, 87, 90, 71, 75, 60, 59, 92, 79, 83, 77, 76, 73, 72, 63, 61, 55, 93, 85, 74, 68, 65, 62, 58, 56, 54, 53, 49, 48] },
	{ "s": "ЧУВСТВИТЕЛЬНОЙ", "p": [68] }
]