[
	{ "s": "VALID", "p": [21] },
	{ "s": "VALUE", "p": [20] },
	{ "s": "VALUES", "p": [4] },
	{ "s": "VARIOUS", "p": [2] },
	{ "s": "VENDOR", "p": [25, 23] },
	{ "s": "VENDORS", "p": [2] },
	{ "s": "VERSION", "p": [14, 13, 4, 2, 22, 15] },
	{ "s": "VERSIONS", "p": [6, 5] },
	{ "s": "VIA", "p": [12, 7, 2] },
	{ "s": "VIBRATIONS", "p": [4] },
	{ "s": "VIBROMONITORING", "p": [25, 27] },
	{ "s": "VIRTUAL", "p": [23, 13, 3] },
	{ "s": "VISUALIZATION", "p": [4] },
	{ "s": "VNC", "p": [7] },
	{ "s": "VOLUME", "p": [2] }
]