[
	{ "s": "G", "p": [25] },
	{ "s": "GANNT", "p": [57] },
	{ "s": "GATEWAY", "p": [59] },
	{ "s": "GAVE", "p": [62] },
	{ "s": "GENERAL", "p": [9, 61, 59, 53, 52, 48] },
	{ "s": "GENERATE", "p": [20] },
	{ "s": "GENERATED", "p": [20] },
	{ "s": "GENERATION", "p": [7] },
	{ "s": "GEOGRAPHICAL", "p": [8] },
	{ "s": "GEOGRAPHICALLY", "p": [8] },
	{ "s": "GET", "p": [57, 58, 52, 26] },
	{ "s": "GHZ", "p": [9] },
	{ "s": "GIVE", "p": [61] },
	{ "s": "GIVEN", "p": [60] },
	{ "s": "GIVES", "p": [59, 62, 61] },
	{ "s": "GLOBAL", "p": [24] },
	{ "s": "GLOBALLY", "p": [57] },
	{ "s": "GO", "p": [53, 51, 50, 48, 25, 12] },
	{ "s": "GOALS", "p": [2] },
	{ "s": "GOES", "p": [31] },
	{ "s": "GOOD", "p": [59] },
	{ "s": "GRANT", "p": [24] },
	{ "s": "GRAPHIC", "p": [61] },
	{ "s": "GRAPHS", "p": [2] },
	{ "s": "GREEN", "p": [32] },
	{ "s": "GROUP", "p": [22, 24, 23, 60, 46, 38, 13] },
	{ "s": "GROUPS", "p": [22, 21, 60, 24, 38, 28, 20, 13] },
	{ "s": "GROWS", "p": [53, 48] },
	{ "s": "GROWTH", "p": [54, 43] },
	{ "s": "GSM", "p": [35] },
	{ "s": "GUARANTEE", "p": [59] },
	{ "s": "GUARANTEES", "p": [59] }
]