[
	{ "s": "3", "p": [31, 27, 5, 14, 13, 88, 71, 68, 23, 20, 15, 93, 59, 54, 49, 47, 39, 36, 32, 30, 25, 21, 9] },
	{ "s": "3.0", "p": [5] },
	{ "s": "3.1", "p": [31, 27, 14] },
	{ "s": "3.2", "p": [31, 27, 14] },
	{ "s": "3.27.2", "p": [5] },
	{ "s": "3.3", "p": [31, 27] },
	{ "s": "3.4", "p": [31] },
	{ "s": "3.5", "p": [31, 5] },
	{ "s": "3.6", "p": [31] },
	{ "s": "3.7", "p": [31] },
	{ "s": "30", "p": [21, 54, 49] },
	{ "s": "300GB", "p": [10] },
	{ "s": "31", "p": [54, 49] },
	{ "s": "32", "p": [54, 49] },
	{ "s": "32GB", "p": [9] },
	{ "s": "33", "p": [54, 49] },
	{ "s": "34", "p": [54, 49] },
	{ "s": "35", "p": [54, 49] },
	{ "s": "36", "p": [54, 49] },
	{ "s": "37", "p": [54, 49] },
	{ "s": "38", "p": [54, 49] },
	{ "s": "39", "p": [54, 49] },
	{ "s": "3D", "p": [64, 13, 2] },
	{ "s": "3D-МОДЕЛИ", "p": [64] },
	{ "s": "3D-МОДЕЛЬЮ", "p": [64] },
	{ "s": "3D–МОДЕЛИ", "p": [64] }
]